drupdates/__init__.py
drupdates/cli.py
drupdates/demo.py
drupdates/drush.py
drupdates/plugins.py
drupdates/settings.py
drupdates/sitebuild.py
drupdates/siteupdate.py
drupdates/updates.py
drupdates/utils.py
drupdates/constructors/__init__.py
drupdates/constructors/pmtools.py
drupdates/constructors/reports.py
drupdates/constructors/repos.py
drupdates/plugins/File/__init__.py
drupdates/plugins/File/settings/default.yaml
drupdates/plugins/Repolist/__init__.py
drupdates/plugins/Repolist/settings/default.yaml
drupdates/plugins/Sendmail/__init__.py
drupdates/plugins/Sendmail/settings/default.yaml
drupdates/plugins/Stdout/__init__.py
drupdates/settings/default.yaml
drupdates/templates/aliases.template
drupdates/templates/settings.template
drupdates/tests/__init__.py
drupdates/tests/behavioral/__init__.py
drupdates/tests/behavioral/behavioral_utils.py
drupdates/tests/behavioral/test_custom_working_settings.py
drupdates/tests/behavioral/test_debug_report.py
drupdates/tests/behavioral/test_drush_make.py
drupdates/tests/behavioral/test_drush_make_custom.py
drupdates/tests/behavioral/test_drush_make_webroot.py
drupdates/tests/behavioral/test_feature_branch.py
drupdates/tests/behavioral/test_json_report.py
drupdates/tests/behavioral/test_multiple_sites.py
drupdates/tests/behavioral/test_multiple_sites_one_noupdates.py
drupdates/tests/behavioral/test_multiple_sites_option_single_site.py
drupdates/tests/behavioral/test_multiple_working_directories.py
drupdates/tests/behavioral/test_multiple_working_directories_multiple_sites.py
drupdates/tests/behavioral/test_multiple_working_directories_one_site.py
drupdates/tests/behavioral/test_multiple_working_directories_single_site.py
drupdates/tests/behavioral/test_multiple_working_directories_working_directory_cli.py
drupdates/tests/behavioral/test_noupdates.py
drupdates/tests/behavioral/test_noupdates_multisites.py
drupdates/tests/behavioral/test_simple.py
Drupdates-1.5.2.dist-info/DESCRIPTION.rst
Drupdates-1.5.2.dist-info/entry_points.txt
Drupdates-1.5.2.dist-info/METADATA
Drupdates-1.5.2.dist-info/metadata.json
Drupdates-1.5.2.dist-info/RECORD
Drupdates-1.5.2.dist-info/top_level.txt
Drupdates-1.5.2.dist-info/WHEEL
