Metadata-Version: 2.0
Name: Drupdates
Version: 1.5.2
Summary: Drupal updates scripts
Home-page: https://github.com/jalama/drupdates
Author: Jim Taylor
Author-email: jalama@gmail.com
License: UNKNOWN
Download-URL: https://github.com/jalama/drupdates
Platform: UNKNOWN
Classifier: Development Status :: 5 - Production/Stable
Classifier: Environment :: Console
Classifier: Intended Audience :: Developers
Classifier: Intended Audience :: System Administrators
Classifier: License :: OSI Approved :: MIT License
Classifier: Natural Language :: English
Classifier: Operating System :: MacOS :: MacOS X
Classifier: Operating System :: POSIX
Classifier: Programming Language :: Python
Classifier: Programming Language :: Python :: 2
Classifier: Programming Language :: Python :: 2.6
Classifier: Programming Language :: Python :: 2.7
Classifier: Programming Language :: Python :: 3
Classifier: Programming Language :: Python :: 3.3
Classifier: Programming Language :: Python :: 3.4
Classifier: Programming Language :: Python :: 3.5
Classifier: Topic :: System :: Systems Administration
Classifier: Topic :: Software Development :: Build Tools
Classifier: Topic :: Software Development :: Bug Tracking
Requires-Dist: nose
Requires-Dist: gitpython
Requires-Dist: requests
Requires-Dist: pyyaml
